{
  "project_info": {
    "project_number": "230578974010",
    "firebase_url": "https://elf-student-e0f2d.firebaseio.com",
    "project_id": "elf-student-e0f2d",
    "storage_bucket": "elf-student-e0f2d.appspot.com"
  },
  "client": [
    {
      "client_info": {
        "mobilesdk_app_id": "1:230578974010:android:975b67cb45850d90",
        "android_client_info": {
          "package_name": "com.elf.elfstudent"
        }
      },
      "oauth_client": [
        {
          "client_id": "230578974010-p41ugqine18bbjcpcpufui73knl2d4p2.apps.googleusercontent.com",
          "client_type": 1,
          "android_info": {
            "package_name": "com.elf.elfstudent",
            "certificate_hash": "A61F116E0E5A32526D453A4BCCE982B5AD58820B"
          }
        },
        {
          "client_id": "230578974010-chachjid607pq1aqk7vfhlv8p56f5752.apps.googleusercontent.com",
          "client_type": 1,
          "android_info": {
            "package_name": "com.elf.elfstudent",
            "certificate_hash": "A5E29B98A47EEEAE03B6A37A91B59600871FCC46"
          }
        },
        {
          "client_id": "230578974010-65qv65nv8elhp8rev0b8lhv9bunlehjo.apps.googleusercontent.com",
          "client_type": 3
        }
      ],
      "api_key": [
        {
          "current_key": "AIzaSyCtJ6r8yssE3kuw31pmkBsQohIErDzTILw"
        }
      ],
      "services": {
        "analytics_service": {
          "status": 1
        },
        "appinvite_service": {
          "status": 2,
          "other_platform_oauth_client": [
            {
              "client_id": "230578974010-65qv65nv8elhp8rev0b8lhv9bunlehjo.apps.googleusercontent.com",
              "client_type": 3
            }
          ]
        },
        "ads_service": {
          "status": 2
        }
      }
    }
  ],
  "configuration_version": "1"
}